{
  "_class": "shapeGroup",
  "clippingMaskMode": 0,
  "do_objectID": "44CB5BEC-DC9D-4A2B-B269-05E6B3E137A2",
  "exportOptions": {
    "_class": "exportOptions",
    "do_objectID": "06E05BF4-BA1D-43B3-A65B-36DE8075D93B",
    "exportFormats": [
    ],
    "includedLayerIds": [
    ],
    "layerOptions": 0,
    "shouldTrim": false
  },
  "frame": {
    "_class": "rect",
    "constrainProportions": false,
    "do_objectID": "DFD49D34-DB2B-46BB-B929-567DCACBF789",
    "height": 69,
    "width": 185,
    "x": 0,
    "y": 0
  },
  "hasClickThrough": false,
  "hasClippingMask": false,
  "isFlippedHorizontal": false,
  "isFlippedVertical": false,
  "isLocked": false,
  "isVisible": true,
  "layerListExpandedType": 1,
  "layers": [
    {
      "class": "rectangle",
      "id": "81171F78-5077-40A1-A0E6-9E09975093B8"
    }
  ],
  "name": "Rectangle 6",
  "nameIsFixed": false,
  "resizingConstraint": 63,
  "resizingType": 0,
  "rotation": 0,
  "shouldBreakMaskChain": false,
  "style": {
    "_class": "style",
    "borders": [
      {
        "_class": "border",
        "color": {
          "_class": "color",
          "alpha": 1,
          "blue": 0.592,
          "green": 0.592,
          "red": 0.592
        },
        "fillType": 0,
        "isEnabled": false,
        "position": 1,
        "thickness": 1
      }
    ],
    "do_objectID": "A26EF5C6-F014-40F5-AD57-1980DAF21557",
    "endDecorationType": 0,
    "fills": [
      {
        "_class": "fill",
        "color": {
          "_class": "color",
          "alpha": 1,
          "blue": 0.6549019607843137,
          "green": 0.2627450980392157,
          "red": 0.5372549019607844
        },
        "fillType": 0,
        "isEnabled": true,
        "noiseIndex": 0,
        "noiseIntensity": 0,
        "patternFillType": 1,
        "patternTileScale": 1
      }
    ],
    "miterLimit": 10,
    "shadows": [
      {
        "_class": "shadow",
        "blurRadius": 8,
        "color": {
          "_class": "color",
          "alpha": 0.5,
          "blue": 0.7872555272108843,
          "green": 0.7872555272108843,
          "red": 0.7872555272108843
        },
        "contextSettings": {
          "_class": "graphicsContextSettings",
          "blendMode": 0,
          "opacity": 1
        },
        "isEnabled": false,
        "offsetX": 0,
        "offsetY": 0,
        "spread": 2
      }
    ],
    "startDecorationType": 0
  },
  "windingRule": 1
}